mlops_build/__init__.py
mlops_build/predict_model.py
mlops_build/train_model.py
mlops_build/validate_model.py
mlops_build-0.1.1.dist-info/entry_points.txt
mlops_build-0.1.1.dist-info/WHEEL
mlops_build-0.1.1.dist-info/METADATA
mlops_build-0.1.1.dist-info/RECORD
